LICENSE.md
MANIFEST.in
README.rst
setup.cfg
setup.py
docs/build/html/beyond.html
docs/build/html/clients.html
docs/build/html/examples.html
docs/build/html/features.html
docs/build/html/genindex.html
docs/build/html/high-level.html
docs/build/html/hl-api-docstrings.html
docs/build/html/http.html
docs/build/html/hub.html
docs/build/html/index.html
docs/build/html/introduction.html
docs/build/html/ll-api-docstrings.html
docs/build/html/low-level.html
docs/build/html/message.html
docs/build/html/microservice.html
docs/build/html/parts.html
docs/build/html/pipeline.html
docs/build/html/py-modindex.html
docs/build/html/registry.html
docs/build/html/search.html
docs/build/html/searchindex.js
docs/build/html/servers.html
docs/build/html/workers.html
docs/build/html/_images/core.png
docs/build/html/_images/http_part.png
docs/build/html/_images/master_internals.png
docs/build/html/_images/master_pipeline.png
docs/build/html/_images/microservice_internals.png
docs/build/html/_images/parallel.png
docs/build/html/_images/parallel_http.png
docs/build/html/_images/pipeline-stream-sink.png
docs/build/html/_images/pipeline-stream.png
docs/build/html/_images/pipeline-tee.png
docs/build/html/_images/pipeline.png
docs/build/html/_images/server_hub.png
docs/build/html/_images/single.png
docs/build/html/_modules/index.html
docs/build/html/_modules/socketserver.html
docs/build/html/_modules/http/server.html
docs/build/html/_modules/pylm/clients.html
docs/build/html/_modules/pylm/servers.html
docs/build/html/_modules/pylm/parts/connections.html
docs/build/html/_modules/pylm/parts/core.html
docs/build/html/_modules/pylm/parts/gateways.html
docs/build/html/_modules/pylm/parts/servers.html
docs/build/html/_modules/pylm/parts/services.html
docs/build/html/_static/README.md
docs/build/html/_static/ajax-loader.gif
docs/build/html/_static/basic.css
docs/build/html/_static/comment-bright.png
docs/build/html/_static/comment-close.png
docs/build/html/_static/comment.png
pylm.egg-info/PKG-INFO
pylm.egg-info/SOURCES.txt
pylm.egg-info/dependency_links.txt
pylm.egg-info/requires.txt
pylm.egg-info/top_level.txt
